pandaq/__init__.py
pandaq/config.py
pandaq/patch.py
pandaq/query.py
pandaq/utils.py
pandaq/vtypes/__init__.py
pandaq/vtypes/base.py
pandaq/vtypes/boolean.py
pandaq/vtypes/datetimes.py
pandaq/vtypes/ntuple.py
pandaq/vtypes/number.py
pandaq/vtypes/string.py
pandaq-0.1.0.dist-info/LICENSE
pandaq-0.1.0.dist-info/METADATA
pandaq-0.1.0.dist-info/WHEEL
pandaq-0.1.0.dist-info/top_level.txt
pandaq-0.1.0.dist-info/RECORD
