Metadata-Version: 2.1
Name: pandaq
Version: 0.1.0
Summary: An easy pandas query-string builder.
Author-email: eholic <task@mxxiv.net>
Maintainer-email: eholic <task@mxxiv.net>
License: MIT License
Project-URL: Repository, https://github.com/eholic/pandaq
Classifier: Development Status :: 4 - Beta
Classifier: Intended Audience :: Science/Research
Classifier: Topic :: Scientific/Engineering
Classifier: License :: OSI Approved :: MIT License
Classifier: Programming Language :: Python :: 3
Classifier: Programming Language :: Python :: 3.9
Classifier: Programming Language :: Python :: 3.10
Classifier: Programming Language :: Python :: 3.11
Classifier: Programming Language :: Python :: 3.12
Classifier: Programming Language :: Python :: 3 :: Only
Requires-Python: >=3.9
License-File: LICENSE
Requires-Dist: pandas
